{
  "display": {
    "icon": {
      "item": "compressedblocks:c8_gravel"
    },
    "title": "沙砾狂热： IX",
    "description": "§5把9个八重压缩§2沙砾§5制成九重压缩§2沙砾",
    "frame": "challenge",
    "show_toast": true,
    "announce_to_chat": true,
    "hidden": false
  },
  "parent": "compressedblocks:addiction/c7_gravel_edition",
  "criteria": {
    "get_c8_gravel_edition": {
      "trigger": "minecraft:inventory_changed",
      "conditions": {
        "items": [
          {
            "items": [
              "compressedblocks:c8_gravel"
            ]
          }
        ]
      }
    }
  },
  "requirements": [
    [
      "get_c8_gravel_edition"
    ]
  ],
  "rewards": {
    "experience": 6000
  },
  "sends_telemetry_event": true
}
