{
  "display": {
    "icon": {
      "item": "compressedblocks:double_crated_apple"
    },
    "title": "更多箱子！！！",
    "description": "把箱装物品继续装箱",
    "frame": "task",
    "show_toast": true,
    "announce_to_chat": true,
    "hidden": false
  },
  "parent": "compressedblocks:compression/crate",
  "criteria": {
    "get_double_crate": {
      "trigger": "minecraft:inventory_changed",
      "conditions": {
        "items": [
          {
            "tag": "compressedblocks:double_crate"
          }
        ]
      }
    }
  },
  "requirements": [
    [
      "get_double_crate"
    ]
  ],
  "rewards": {
    "experience": 500
  },
  "sends_telemetry_event": true
}
